ellipsetools/__init__.py
ellipsetools/ellipse.py
ellipsetools/subdivide_ellipse.py
ellipsetools-0.0.5.dist-info/METADATA
ellipsetools-0.0.5.dist-info/WHEEL
ellipsetools-0.0.5.dist-info/licenses/LICENSE
ellipsetools-0.0.5.dist-info/RECORD
