Metadata-Version: 2.1
Name: ellipsetools
Version: 0.0.5
Summary: Equal subdivision of an ellipse into N points
Project-URL: Homepage, https://github.com/philipwastakenwastaken/ellipse-equal-point-division
Project-URL: Bug Tracker, https://github.com/philipwastakenwastaken/ellipse-equal-point-division/issues
Author-email: Philip Nielsen <philiptofte@hotmail.com>
License: Copyright (c) 2022 Philip Nielsen
License-File: LICENSE
Keywords: arc length,ellipse,perimeter,subdivision
Classifier: License :: OSI Approved :: MIT License
Classifier: Operating System :: OS Independent
Classifier: Programming Language :: Python :: 3
Requires-Python: >=3.8
Requires-Dist: numpy
Requires-Dist: scipy
